CPU/datamem.sv
module datamem #(
    parameter ADDRESS_WIDTH = 32,
              DATA_WIDTH = 32
)(
    input logic clk,
    input logic [ADDRESS_WIDTH-1:0] A,    
    input logic [ADDRESS_WIDTH-1:0] WD,
    input logic WE,

    output logic [DATA_WIDTH-1:0] RD,

);

    logic [DATA_WIDTH-1:0] ram_array [2**ADDRESS_WIDTH-1:0];

    always_comb begin
        RD = ram_array[A];
    end

    initial begin
        for (int i = 0; i< $size(ram_array); i++) begin
            ram_array[i] = 32'b0;
        end
    end

    always_ff @ (posedge clk) begin
        if (WE)  ram_array[A] <= WD;
    end

endmodule

CPU/ALU.sv
module ALU #(
    parameter 
              DATA_WIDTH = 32
)(
    input logic [DATA_WIDTH-1:0] ALUop1,
    input logic [DATA_WIDTH-1:0] ALUop2,
    input logic [2:0] ALUctrl,
    
    output logic [DATA_WIDTH-1:0] ALUout,
    output logic Zero

);

    always_comb begin
    
        casez (ALUctrl)
            3'b000:  ALUout = ALUop1 + ALUop2;      //add
            3'b001:  ALUout = ALUop1 - ALUop2;      //subtract
            3'b010:  ALUout = ALUop1 & ALUop2;      //bitwise and
            3'b011:  ALUout = ALUop1 | ALUop2;      //bitwise or
            3'b100:  ALUout = ALUop1 ^ ALUop2;      //bitwise xor
            3'b110:  ALUout = ALUop1 << ALUop2;     //logical shift left by ALUop2
            3'b111:  ALUout = ALUop1 >> ALUop2;     //logical right shift by ALUop2
            
            // 3'b101:  slt, which is not used

           default: ALUout = ALUop2;                //for LUI where Imm has to pass through 
    
        endcase
    
     end
     
     assign Zero = (ALUop1 - ALUop2 == 0) ? 1'b1 : 1'b0; //for bne

endmodule

CPU/ram.sv
module ram #(
    parameter ADDRESS_WIDTH = 5,
              DATA_WIDTH = 32
)(
    input logic clk,
    input logic [ADDRESS_WIDTH-1:0] AD1,    
    input logic [ADDRESS_WIDTH-1:0] AD2,
    input logic [ADDRESS_WIDTH-1:0] AD3,

    input logic WE3,
    input logic [DATA_WIDTH-1:0] WD3,

    output logic [DATA_WIDTH-1:0] a0,
    output logic [DATA_WIDTH-1:0] RD1,
    output logic [DATA_WIDTH-1:0] RD2

);

    logic [DATA_WIDTH-1:0] ram_array [2**ADDRESS_WIDTH-1:0];
//assign ram_array[5'b00000] = {DATA_WIDTH{1'b0}};
    always_comb begin
        RD1 = ram_array[AD1];
        RD2 = ram_array [AD2];
    end

    initial begin
        for (int i = 0; i< $size(ram_array); i++) begin
            ram_array[i] = 32'b0;
        end
    end

    always_ff @ (posedge clk) begin
        if (WE3)  ram_array[AD3] <= WD3;
        ram_array[0] <= 1'b0;
    end

    assign a0 = ram_array[10];

endmodule

CPU/red_top.sv
module red_top #(
    parameter ADDRESS_WIDTH = 5,
              ALUctrl_WIDTH = 3,
              DATA_WIDTH = 32
)(
  input logic clk,

  input logic [DATA_WIDTH-1:0] ImmOp,
  input logic RegWrite,
  input logic [ALUctrl_WIDTH-1:0] ALUctrl,
  input logic ALUsrc,
  input logic [ADDRESS_WIDTH-1:0] rs1,
  input logic [ADDRESS_WIDTH-1:0] rs2,
  input logic [ADDRESS_WIDTH-1:0] rd,
  input logic MemWrite,
  input logic [1:0] ResultSrc,
  input logic [DATA_WIDTH-1:0] PCPlus4,

  output logic  Zero,
  output logic [DATA_WIDTH-1:0] a0

);
  
   logic [DATA_WIDTH-1:0] SrcA;
   logic [DATA_WIDTH-1:0] regOp2;
   logic [DATA_WIDTH-1:0] ALUop2;
   logic [DATA_WIDTH-1:0] ALUout;

   logic [DATA_WIDTH-1:0] result;
   logic [DATA_WIDTH-1:0] readata;

  assign ALUop2 = ALUsrc ? ImmOp:regOp2;
  assign result = ResultSrc[1] ? PCPlus4 : (ResultSrc[0] ? readata : ALUout);

ram ram (
  .clk (clk),
  .AD1 (rs1),
  .AD2 (rs2),
  .AD3 (rd),
  .WE3 (RegWrite),
  .WD3 (result),
  .a0 (a0),
  .RD1 (SrcA),
  .RD2 (regOp2)
);

ALU ALU (
   .ALUop1 (SrcA),
   .ALUop2 (ALUop2),
   .ALUctrl (ALUctrl),
   .ALUout (ALUout),
   .Zero (Zero)
);

datamem datamem (
  .RD (readata),
  .clk (clk),
  .A (ALUout),
  .WE (MemWrite),
  .WD (regOp2)
);

endmodule

CPU/extend.sv

module extend #(
    parameter WIDTH = 32
) (
    //interface signals
    input   logic   [WIDTH-1:0]  Instr,                       //32 bit instruction
    input   logic   [1:0]        ImmSrc,                    //Control signal
    output  logic   [WIDTH-1:0]  ImmOp                      //32 bit out
);

always_comb begin
    case(ImmSrc)
        2'b00: ImmOp = { {20{Instr[31]}}, Instr[31:20] };                                               //I-type when ImmSrc = 00
        2'b01: ImmOp = { {20{Instr[31]}}, Instr[31:25], Instr[11:7] };                                  //S-type when ImmSrc = 01
        2'b10: ImmOp = { {20{Instr[31]}}, Instr[7], Instr[30:25], Instr[11:8], 1'b0 };                  //B-type when ImmSrc = 10
        2'b11: ImmOp = { {11{Instr[31]}}, Instr[19:12], Instr[20], Instr[31:25], Instr[24:21], 1'b0};   //J-type when ImmSrc = 11
    endcase
end

endmodule

CPU/decodealu.sv
module decodealu (
    input logic [1:0] ALUOp,
    input logic [6:0] opcode,
    input logic [2:0] fn3,
    input logic [6:0] fn7,

    output logic [2:0] ALUControl
);

logic [6:0] decoder;

assign decoder = {ALUOp, fn3, opcode[5], fn7[5]}; 

always_comb
    casez(decoder)
        //7'b00?????: ALUControl = 000; //handled by default
        //R type
        7'b1000010: ALUControl = 3'b000;    //add
        7'b1000011: ALUControl = 3'b001;    //subtract
        7'b10110??: ALUControl = 3'b011;    //or
        7'b10111??: ALUControl = 3'b010;    //and
        7'b10100??: ALUControl = 3'b100;    //xor

        //B type
        7'b0100???: ALUControl = 3'b001;    //beq, bne

        //I and S types, aluop = 00
        7'b0000100: ALUControl = 3'b110;    //slli, fn7 only matters if more load ins (op 3) are needed
        7'b0010100: ALUControl = 3'b111;    //srli, same as above, also if srai is needed
        7'b00111??: ALUControl = 3'b010;    //andi, fn7 and op dont matter, as op 3 load ins do not have fn3=111
        7'b000001?: ALUControl = 3'b000;    //sb - s type imm(rs1) - add
        7'b001000?: ALUControl = 3'b000;    //lbu - i type imm(rs1) - add

        //U and J types would be ALUOp = 11, but since we only use jal, this is not used
        7'b11???1?: ALUControl = 3'b101;    //lui, for default ALU operation - passes ALUop2 (Imm) straight through

        default: ALUControl = 3'b000;
    endcase

endmodule

CPU/decodemain.sv
module decodemain #(
        parameter D_WIDTH = 32
    )(
    input logic Zero, //AND with Branch
    input logic [D_WIDTH - 1:0] Instr, //last 7 bits of instr go here

    output logic PCSrc, 
    output logic [1:0] ResultSrc,
    output logic MemWrite,
    output logic ALUSrc,
    output logic [1:0] ImmSrc,  
    output logic RegWrite,
    output logic [1:0] ALUOp              
);

logic [6:0] opcode = Instr[6:0];
logic [2:0] fn3 = Instr[14:12];
logic [6:0] fn7 = Instr[31:25];
logic Branch;

always_comb begin
    casez(opcode) 
        7'b0110011: begin //R type
                RegWrite = 1'b1;
                ImmSrc = 2'b00;
                ALUSrc = 1'b0;
                MemWrite = 1'b0;
                ResultSrc = 2'b00;
                ALUOp = 2'b10;
                Branch = 1'b0;
            end
        7'b0000011: begin // I type, op 3. lw only
                RegWrite = 1'b1;
                ImmSrc = 2'b00;
                ALUSrc = 1'b1;
                MemWrite = 1'b0;
                ResultSrc = 2'b01;
                ALUOp = 2'b00;
                Branch = 1'b0;
            end
        7'b0010011: begin // I type, op 19
                RegWrite = 1'b1;
                ImmSrc = 2'b00;
                ALUSrc = 1'b1;
                MemWrite = 1'b0;
                ResultSrc = 2'b00;
                ALUOp = 2'b00;
                Branch = 1'b0;
            end
        7'b0100011: begin // S type
                RegWrite = 1'b0;
                ImmSrc = 2'b01;
                ALUSrc = 1'b1;
                MemWrite = 1'b1;
                ResultSrc = 2'b00;
                ALUOp = 2'b00;
                Branch = 1'b0;
            end
        7'b1100011: begin // B type
                RegWrite = 1'b0;
                ImmSrc = 2'b10;
                ALUSrc = 1'b0;
                MemWrite = 1'b0;
                ResultSrc = 2'b00;
                ALUOp = 2'b01;
                Branch = (fn3 == 3'b001) ? !Zero : Zero; //to invert Zero for bne/beq
            end
        7'b1101111: begin // JAL
                RegWrite = 1'b1;
                ImmSrc = 2'b11; // for J type in the ext 
                ALUSrc = 1'b1;
                MemWrite = 1'b0;
                ResultSrc = 2'b10;
                ALUOp = 2'b00;
                Branch = 1'b1; // unconditional jump
            end
        7'b1100111: begin // JALR
                RegWrite = 1'b1;
                ImmSrc = 2'b00;
                ALUSrc = 1'b1;
                MemWrite = 1'b0;
                ResultSrc = 2'b10;
                ALUOp = 2'b00;
                Branch = 1'b1; // unconditional jump
            end
        default: begin
            RegWrite = 1'b0;
            ImmSrc = 2'b00;
            ALUSrc = 1'b0;
            MemWrite = 1'b0;
            ResultSrc = 2'b00;
            ALUOp = 2'b0;
            Branch = 1'b0;
        end
    endcase

    assign PCSrc = Branch ? 1'b1 : 1'b0;        //PCSrc cannot be assigned in case - has to assigned sequentially after control signals assigned to use zero correctly

end

endmodule

CPU/control.sv
module control #(
    parameter D_WIDTH = 32
)(
    input logic Zero, //what does this do?
    input logic [D_WIDTH-1:0] Instr, //will need more than this later , for fn3 and 7

    output logic PCSrc, 
    output logic [1:0] ResultSrc,
    output logic MemWrite,
    output logic [2:0] ALUControl,
    output logic ALUSrc,
    output logic [1:0] ImmSrc,  
    output logic RegWrite                
);

logic [1:0] ALUOp; 

decodemain dmain(
    //.opcode(Instr[6:0]),
    .Instr(Instr),
    .Zero(Zero),
    .PCSrc(PCSrc), 
    .ResultSrc(ResultSrc),
    .MemWrite(MemWrite),
    .ALUSrc(ALUSrc),
    .ImmSrc(ImmSrc),  
    .RegWrite(RegWrite),
    .ALUOp(ALUOp)
);

decodealu dalu(
    .opcode(Instr[6:0]),
    .ALUOp(ALUOp),
    .fn3(Instr[14:12]),
    .fn7(Instr[31:25]),
    .ALUControl(ALUControl)
);

endmodule

CPU/instrmem.sv
module instrmem #(
    parameter D_WIDTH = 8, // For byte addressing
              A_WIDTH = 12, //Due to memory map, instr mem has 000 to FFF, so 12 bits
              EXT_WIDTH = 32 //Signals from PC and the output are both 32 bits
) (
    //input logic clk,
    input logic [EXT_WIDTH-1:0] A,
    output logic [EXT_WIDTH-1:0] RD //output is 32 bits
);

logic [A_WIDTH-1:0] Addr = A[A_WIDTH-1:0];
logic [D_WIDTH-1:0] rom_array [2**A_WIDTH-1:0]; //each data stored is 8bits, and the rom size is 2^12 bits

initial begin
    $readmemh("assembly.s.hex", rom_array); //read from this hex file
end

assign RD = {rom_array [Addr + 3], rom_array [Addr + 2], rom_array [Addr + 1], rom_array [Addr]};

endmodule

CPU-2/modules/PC_Reg.sv
module PC_Reg #(
    parameter WIDTH = 32
)(
  input logic              clk,
  input logic              rst,
  input logic  [WIDTH-1:0] next_PC,
  output logic [WIDTH-1:0] PC

);

always_ff @ (posedge clk, posedge rst)
  if (rst) PC <= 32'b0;
  else     PC <= next_PC;

endmodule

CPU/PC_top.sv
module PC_top #(
  parameter WIDTH = 32


)(
  input logic    clk,
  input logic    rst,
  input logic [WIDTH-1:0] ImmOp, 
  input logic PCsrc,
  output logic [WIDTH-1:0] PC,
  output logic [WIDTH-1:0] PCPlus4
);
  logic [WIDTH-1:0] next_PC;
  logic [WIDTH-1:0] branch_PC;

  assign PCPlus4 = PC + 4;
  assign branch_PC = PC + ImmOp; 

  assign next_PC = PCsrc ? branch_PC : PCPlus4;

/*Mux_1 Mux_1 (
  .PCsrc (PCsrc),
  .inc_PC (inc_PC),
  .branch_PC (branch_PC),
  .next_PC (next_PC)
);
*/
PC_Reg PC_Reg
 (
  .clk (clk),
  .rst (rst),
  .next_PC (next_PC),
  .PC (PC)
);

endmodule

CPU/cpu.sv
module cpu #(
    parameter ADDRESS_WIDTH = 32
)(
    input clk,
    input rst,
    output [ADDRESS_WIDTH-1:0] a0

);
   
    // logic [ADDRESS_WIDTH-1:0] instr;
    // logic ImmSrc;
    logic Zero;
    logic [ADDRESS_WIDTH-1:0] PC;
    logic [ADDRESS_WIDTH-1:0] PCPlus4;
    logic [ADDRESS_WIDTH-1:0] ImmOp;
    logic PCsrc;
    logic RegWrite;
    logic [3-1:0] ALUctrl; //needs to be 3 bit
    logic ALUsrc;
    logic [1:0] ImmSrc;
    logic [ADDRESS_WIDTH-1:0] instr;
    logic [1:0] ResultSrc;
    logic MemWrite;

//blue
PC_top blue (
  .clk(clk),
  .rst(rst),
  .ImmOp(ImmOp),
  .PCsrc(PCsrc),
  .PC(PC),
  .PCPlus4(PCPlus4)
);

//green
instrmem rom (
    .A(PC),
    .RD(instr)
);

control ctrl (
    .Instr(instr), //how to take the last 7 bits of instr from rom
    .Zero(Zero),
    .PCSrc(PCsrc),
    .ResultSrc(ResultSrc),
    .MemWrite(MemWrite),
    .ALUControl(ALUctrl),
    .ALUSrc(ALUsrc),
    .ImmSrc(ImmSrc),
    .RegWrite(RegWrite)
);

extend sign_ext (
    .Instr(instr),  //same here
    .ImmSrc(ImmSrc),
    .ImmOp(ImmOp)
);

//red
red_top red(
  .ImmOp(ImmOp),
  .clk(clk),
  .RegWrite(RegWrite),
  .MemWrite(MemWrite),
  .ALUctrl(ALUctrl),
  .ALUsrc(ALUsrc),
  .rs1(instr[19:15]),
  .rs2(instr[24:20]), 
  .rd(instr[11:7]),
  .Zero(Zero),
  .ResultSrc(ResultSrc),
  .a0(a0),
  .PCPlus4(PCPlus4)
);

endmodule

CPU/cpu.vcd
$version Generated by VerilatedVcd $end
$date Wed Dec  7 18:41:03 2022 $end
$timescale 1ps $end

 $scope module TOP $end
  $var wire 32 e a0 [31:0] $end
  $var wire  1 c clk $end
  $var wire  1 d rst $end
  $scope module cpu $end
   $var wire 32 h ADDRESS_WIDTH [31:0] $end
   $var wire  3 M ALUctrl [2:0] $end
   $var wire  1 N ALUsrc $end
   $var wire 32 J ImmOp [31:0] $end
   $var wire  2 O ImmSrc [1:0] $end
   $var wire  1 R MemWrite $end
   $var wire 32 H PC [31:0] $end
   $var wire 32 I PCPlus4 [31:0] $end
   $var wire  1 K PCsrc $end
   $var wire  1 L RegWrite $end
   $var wire  2 Q ResultSrc [1:0] $end
   $var wire  1 G Zero $end
   $var wire 32 e a0 [31:0] $end
   $var wire  1 c clk $end
   $var wire 32 P instr [31:0] $end
   $var wire  1 d rst $end
   $scope module blue $end
    $var wire 32 J ImmOp [31:0] $end
    $var wire 32 H PC [31:0] $end
    $var wire 32 I PCPlus4 [31:0] $end
    $var wire  1 K PCsrc $end
    $var wire 32 h WIDTH [31:0] $end
    $var wire 32 T branch_PC [31:0] $end
    $var wire  1 c clk $end
    $var wire 32 S next_PC [31:0] $end
    $var wire  1 d rst $end
    $scope module PC_Reg $end
     $var wire 32 H PC [31:0] $end
     $var wire 32 h WIDTH [31:0] $end
     $var wire  1 c clk $end
     $var wire 32 S next_PC [31:0] $end
     $var wire  1 d rst $end
    $upscope $end
   $upscope $end
   $scope module ctrl $end
    $var wire  3 M ALUControl [2:0] $end
    $var wire  2 U ALUOp [1:0] $end
    $var wire  1 N ALUSrc $end
    $var wire 32 h D_WIDTH [31:0] $end
    $var wire  2 O ImmSrc [1:0] $end
    $var wire 32 P Instr [31:0] $end
    $var wire  1 R MemWrite $end
    $var wire  1 K PCSrc $end
    $var wire  1 L RegWrite $end
    $var wire  2 Q ResultSrc [1:0] $end
    $var wire  1 G Zero $end
    $scope module dalu $end
     $var wire  3 M ALUControl [2:0] $end
     $var wire  2 U ALUOp [1:0] $end
     $var wire  7 Y decoder [6:0] $end
     $var wire  3 W fn3 [2:0] $end
     $var wire  7 X fn7 [6:0] $end
     $var wire  7 V opcode [6:0] $end
    $upscope $end
    $scope module dmain $end
     $var wire  2 U ALUOp [1:0] $end
     $var wire  1 N ALUSrc $end
     $var wire  1 Z Branch $end
     $var wire 32 h D_WIDTH [31:0] $end
     $var wire  2 O ImmSrc [1:0] $end
     $var wire 32 P Instr [31:0] $end
     $var wire  1 R MemWrite $end
     $var wire  1 K PCSrc $end
     $var wire  1 L RegWrite $end
     $var wire  2 Q ResultSrc [1:0] $end
     $var wire  1 G Zero $end
     $var wire  3 W fn3 [2:0] $end
     $var wire  7 X fn7 [6:0] $end
     $var wire  7 V opcode [6:0] $end
    $upscope $end
   $upscope $end
   $scope module red $end
    $var wire 32 i ADDRESS_WIDTH [31:0] $end
    $var wire  3 M ALUctrl [2:0] $end
    $var wire 32 j ALUctrl_WIDTH [31:0] $end
    $var wire 32 ` ALUop2 [31:0] $end
    $var wire 32 a ALUout [31:0] $end
    $var wire  1 N ALUsrc $end
    $var wire 32 h DATA_WIDTH [31:0] $end
    $var wire 32 J ImmOp [31:0] $end
    $var wire  1 R MemWrite $end
    $var wire 32 I PCPlus4 [31:0] $end
    $var wire  1 L RegWrite $end
    $var wire  2 Q ResultSrc [1:0] $end
    $var wire 32 ^ SrcA [31:0] $end
    $var wire  1 G Zero $end
    $var wire 32 e a0 [31:0] $end
    $var wire  1 c clk $end
    $var wire  5 ] rd [4:0] $end
    $var wire 32 g readata [31:0] $end
    $var wire 32 _ regOp2 [31:0] $end
    $var wire 32 f result [31:0] $end
    $var wire  5 [ rs1 [4:0] $end
    $var wire  5 \ rs2 [4:0] $end
    $scope module ALU $end
     $var wire  3 M ALUctrl [2:0] $end
     $var wire 32 ^ ALUop1 [31:0] $end
     $var wire 32 ` ALUop2 [31:0] $end
     $var wire 32 a ALUout [31:0] $end
     $var wire 32 h DATA_WIDTH [31:0] $end
     $var wire  1 G Zero $end
    $upscope $end
    $scope module datamem $end
     $var wire 32 a A [31:0] $end
     $var wire 32 h ADDRESS_WIDTH [31:0] $end
     $var wire 32 h DATA_WIDTH [31:0] $end
     $var wire 32 g RD [31:0] $end
     $var wire 32 _ WD [31:0] $end
     $var wire  1 R WE $end
     $var wire  1 c clk $end
     $var wire 32 % ram_array[-1] [31:0] $end
     $var wire 32 & ram_array[0] [31:0] $end
     $scope module unnamedblk1 $end
      $var wire 32 # i [31:0] $end
     $upscope $end
    $upscope $end
    $scope module ram $end
     $var wire  5 [ AD1 [4:0] $end
     $var wire  5 \ AD2 [4:0] $end
     $var wire  5 ] AD3 [4:0] $end
     $var wire 32 i ADDRESS_WIDTH [31:0] $end
     $var wire 32 h DATA_WIDTH [31:0] $end
     $var wire 32 ^ RD1 [31:0] $end
     $var wire 32 _ RD2 [31:0] $end
     $var wire 32 f WD3 [31:0] $end
     $var wire  1 L WE3 $end
     $var wire 32 e a0 [31:0] $end
     $var wire  1 c clk $end
     $var wire 32 ' ram_array[0] [31:0] $end
     $var wire 32 1 ram_array[10] [31:0] $end
     $var wire 32 2 ram_array[11] [31:0] $end
     $var wire 32 3 ram_array[12] [31:0] $end
     $var wire 32 4 ram_array[13] [31:0] $end
     $var wire 32 5 ram_array[14] [31:0] $end
     $var wire 32 6 ram_array[15] [31:0] $end
     $var wire 32 7 ram_array[16] [31:0] $end
     $var wire 32 8 ram_array[17] [31:0] $end
     $var wire 32 9 ram_array[18] [31:0] $end
     $var wire 32 : ram_array[19] [31:0] $end
     $var wire 32 ( ram_array[1] [31:0] $end
     $var wire 32 ; ram_array[20] [31:0] $end
     $var wire 32 < ram_array[21] [31:0] $end
     $var wire 32 = ram_array[22] [31:0] $end
     $var wire 32 > ram_array[23] [31:0] $end
     $var wire 32 ? ram_array[24] [31:0] $end
     $var wire 32 @ ram_array[25] [31:0] $end
     $var wire 32 A ram_array[26] [31:0] $end
     $var wire 32 B ram_array[27] [31:0] $end
     $var wire 32 C ram_array[28] [31:0] $end
     $var wire 32 D ram_array[29] [31:0] $end
     $var wire 32 ) ram_array[2] [31:0] $end
     $var wire 32 E ram_array[30] [31:0] $end
     $var wire 32 F ram_array[31] [31:0] $end
     $var wire 32 * ram_array[3] [31:0] $end
     $var wire 32 + ram_array[4] [31:0] $end
     $var wire 32 , ram_array[5] [31:0] $end
     $var wire 32 - ram_array[6] [31:0] $end
     $var wire 32 . ram_array[7] [31:0] $end
     $var wire 32 / ram_array[8] [31:0] $end
     $var wire 32 0 ram_array[9] [31:0] $end
     $scope module unnamedblk1 $end
      $var wire 32 $ i [31:0] $end
     $upscope $end
    $upscope $end
   $upscope $end
   $scope module rom $end
    $var wire 32 H A [31:0] $end
    $var wire 32 l A_WIDTH [31:0] $end
    $var wire 12 b Addr [11:0] $end
    $var wire 32 k D_WIDTH [31:0] $end
    $var wire 32 h EXT_WIDTH [31:0] $end
    $var wire 32 P RD [31:0] $end
   $upscope $end
   $scope module sign_ext $end
    $var wire 32 J ImmOp [31:0] $end
    $var wire  2 O ImmSrc [1:0] $end
    $var wire 32 P Instr [31:0] $end
    $var wire 32 h WIDTH [31:0] $end
   $upscope $end
  $upscope $end
 $upscope $end
$enddefinitions $end


#0
b00000000000000000000000000000000 #
b00000000000000000000000000000000 $
b00000000000000000000000000000000 %
b00000000000000000000000000000000 &
b00000000000000000000000000000000 '
b00000000000000000000000000000000 (
b00000000000000000000000000000000 )
b00000000000000000000000000000000 *
b00000000000000000000000000000000 +
b00000000000000000000000000000000 ,
b00000000000000000000000000000000 -
b00000000000000000000000000000000 .
b00000000000000000000000000000000 /
b00000000000000000000000000000000 0
b00000000000000000000000000000000 1
b00000000000000000000000000000000 2
b00000000000000000000000000000000 3
b00000000000000000000000000000000 4
b00000000000000000000000000000000 5
b00000000000000000000000000000000 6
b00000000000000000000000000000000 7
b00000000000000000000000000000000 8
b00000000000000000000000000000000 9
b00000000000000000000000000000000 :
b00000000000000000000000000000000 ;
b00000000000000000000000000000000 <
b00000000000000000000000000000000 =
b00000000000000000000000000000000 >
b00000000000000000000000000000000 ?
b00000000000000000000000000000000 @
b00000000000000000000000000000000 A
b00000000000000000000000000000000 B
b00000000000000000000000000000000 C
b00000000000000000000000000000000 D
b00000000000000000000000000000000 E
b00000000000000000000000000000000 F
0G
b00000000000000000000000000000000 H
b00000000000000000000000000000100 I
b00000000000000000000000000000000 J
0K
0L
b000 M
0N
b00 O
b00000000000000000000000000000000 P
b00 Q
0R
b00000000000000000000000000000100 S
b00000000000000000000000000000000 T
b00 U
b0000000 V
b000 W
b0000000 X
b0000000 Y
0Z
b00000 [
b00000 \
b00000 ]
b00000000000000000000000000000000 ^
b00000000000000000000000000000000 _
b00000000000000000000000000000000 `
b00000000000000000000000000000000 a
b000000000000 b
1c
0d
b00000000000000000000000000000000 e
b00000000000000000000000000000000 f
b00000000000000000000000000000000 g
b00000000000000000000000000100000 h
b00000000000000000000000000000101 i
b00000000000000000000000000000011 j
b00000000000000000000000000001000 k
b00000000000000000000000000001100 l
#1
b00000000000000000000000000000010 #
b00000000000000000000000000100000 $
b00000000000000000000000011111111 J
1L
1N
b00001111111100000000001100010011 P
b00000000000000000000000011111111 T
b0010011 V
b0000111 X
b11111 \
b00110 ]
b00000000000000000000000011111111 `
b00000000000000000000000011111111 a
0c
b00000000000000000000000011111111 f
#2
b00000000000000000000000011111111 -
1G
b00000000000000000000000000000100 H
b00000000000000000000000000001000 I
b00000000000000000000000000000000 J
b00000000000000000000010100010011 P
b00000000000000000000000000001000 S
b00000000000000000000000000000100 T
b0000000 X
b00000 \
b01010 ]
b00000000000000000000000000000000 `
b00000000000000000000000000000000 a
b000000000100 b
1c
b00000000000000000000000000000000 f
#3
0c
#4
b00000000000000000000000000001000 H
b00000000000000000000000000001100 I
b00000000000000000000010110010011 P
b00000000000000000000000000001100 S
b00000000000000000000000000001000 T
b01011 ]
b000000001000 b
1c
#5
0c
#6
b00000000000000000000000000001100 H
b00000000000000000000000000010000 I
b00000000000001011000010100010011 P
b00000000000000000000000000010000 S
b00000000000000000000000000001100 T
b01011 [
b01010 ]
b000000001100 b
1c
#7
0c
#8
0G
b00000000000000000000000000010000 H
b00000000000000000000000000010100 I
b00000000000000000000000000000001 J
b00000000000101011000010110010011 P
b00000000000000000000000000010100 S
b00000000000000000000000000010001 T
b00001 \
b01011 ]
b00000000000000000000000000000001 `
b00000000000000000000000000000001 a
b000000010000 b
1c
b00000000000000000000000000000001 f
#9
0c
#10
b00000000000000000000000000000001 2
b00000000000000000000000000010100 H
b00000000000000000000000000011000 I
b11111111111111111111111111111000 J
1K
0L
b001 M
0N
b10 O
b11111110011001011001110011100011 P
b00000000000000000000000000001100 S
b00000000000000000000000000001100 T
b01 U
b1100011 V
b001 W
b1111111 X
b0100111 Y
1Z
b00110 \
b11001 ]
b00000000000000000000000000000001 ^
b00000000000000000000000011111111 _
b00000000000000000000000011111111 `
b11111111111111111111111100000010 a
b000000010100 b
1c
b11111111111111111111111100000010 f
#11
0c
#12
b00000000000000000000000000001100 H
b00000000000000000000000000010000 I
b00000000000000000000000000000000 J
0K
1L
b000 M
1N
b00 O
b00000000000001011000010100010011 P
b00000000000000000000000000010000 S
b00 U
b0010011 V
b000 W
b0000000 X
b0000000 Y
0Z
b00000 \
b01010 ]
b00000000000000000000000000000000 _
b00000000000000000000000000000000 `
b00000000000000000000000000000001 a
b000000001100 b
1c
b00000000000000000000000000000001 f
#13
0c
#14
b00000000000000000000000000000001 1
1G
b00000000000000000000000000010000 H
b00000000000000000000000000010100 I
b00000000000000000000000000000001 J
b00000000000101011000010110010011 P
b00000000000000000000000000010100 S
b00000000000000000000000000010001 T
b00001 \
b01011 ]
b00000000000000000000000000000001 `
b00000000000000000000000000000010 a
b000000010000 b
1c
b00000000000000000000000000000001 e
b00000000000000000000000000000010 f
#15
0c
#16
b00000000000000000000000000000010 2
0G
b00000000000000000000000000010100 H
b00000000000000000000000000011000 I
b11111111111111111111111111111000 J
1K
0L
b001 M
0N
b10 O
b11111110011001011001110011100011 P
b00000000000000000000000000001100 S
b00000000000000000000000000001100 T
b01 U
b1100011 V
b001 W
b1111111 X
b0100111 Y
1Z
b00110 \
b11001 ]
b00000000000000000000000000000010 ^
b00000000000000000000000011111111 _
b00000000000000000000000011111111 `
b11111111111111111111111100000011 a
b000000010100 b
1c
b11111111111111111111111100000011 f
#17
0c
#18
b00000000000000000000000000001100 H
b00000000000000000000000000010000 I
b00000000000000000000000000000000 J
0K
1L
b000 M
1N
b00 O
b00000000000001011000010100010011 P
b00000000000000000000000000010000 S
b00 U
b0010011 V
b000 W
b0000000 X
b0000000 Y
0Z
b00000 \
b01010 ]
b00000000000000000000000000000000 _
b00000000000000000000000000000000 `
b00000000000000000000000000000010 a
b000000001100 b
1c
b00000000000000000000000000000010 f
#19
0c
#20
b00000000000000000000000000000010 1
b00000000000000000000000000010000 H
b00000000000000000000000000010100 I
b00000000000000000000000000000001 J
b00000000000101011000010110010011 P
b00000000000000000000000000010100 S
b00000000000000000000000000010001 T
b00001 \
b01011 ]
b00000000000000000000000000000001 `
b00000000000000000000000000000011 a
b000000010000 b
1c
b00000000000000000000000000000010 e
b00000000000000000000000000000011 f
#21
0c
#22
b00000000000000000000000000000011 2
b00000000000000000000000000010100 H
b00000000000000000000000000011000 I
b11111111111111111111111111111000 J
1K
0L
b001 M
0N
b10 O
b11111110011001011001110011100011 P
b00000000000000000000000000001100 S
b00000000000000000000000000001100 T
b01 U
b1100011 V
b001 W
b1111111 X
b0100111 Y
1Z
b00110 \
b11001 ]
b00000000000000000000000000000011 ^
b00000000000000000000000011111111 _
b00000000000000000000000011111111 `
b11111111111111111111111100000100 a
b000000010100 b
1c
b11111111111111111111111100000100 f
#23
0c
#24
b00000000000000000000000000001100 H
b00000000000000000000000000010000 I
b00000000000000000000000000000000 J
0K
1L
b000 M
1N
b00 O
b00000000000001011000010100010011 P
b00000000000000000000000000010000 S
b00 U
b0010011 V
b000 W
b0000000 X
b0000000 Y
0Z
b00000 \
b01010 ]
b00000000000000000000000000000000 _
b00000000000000000000000000000000 `
b00000000000000000000000000000011 a
b000000001100 b
1c
b00000000000000000000000000000011 f
#25
0c
#26
b00000000000000000000000000000011 1
b00000000000000000000000000010000 H
b00000000000000000000000000010100 I
b00000000000000000000000000000001 J
b00000000000101011000010110010011 P
b00000000000000000000000000010100 S
b00000000000000000000000000010001 T
b00001 \
b01011 ]
b00000000000000000000000000000001 `
b00000000000000000000000000000100 a
b000000010000 b
1c
b00000000000000000000000000000011 e
b00000000000000000000000000000100 f
#27
0c
#28
b00000000000000000000000000000100 2
b00000000000000000000000000010100 H
b00000000000000000000000000011000 I
b11111111111111111111111111111000 J
1K
0L
b001 M
0N
b10 O
b11111110011001011001110011100011 P
b00000000000000000000000000001100 S
b00000000000000000000000000001100 T
b01 U
b1100011 V
b001 W
b1111111 X
b0100111 Y
1Z
b00110 \
b11001 ]
b00000000000000000000000000000100 ^
b00000000000000000000000011111111 _
b00000000000000000000000011111111 `
b11111111111111111111111100000101 a
b000000010100 b
1c
b11111111111111111111111100000101 f
#29
0c
#30
b00000000000000000000000000001100 H
b00000000000000000000000000010000 I
b00000000000000000000000000000000 J
0K
1L
b000 M
1N
b00 O
b00000000000001011000010100010011 P
b00000000000000000000000000010000 S
b00 U
b0010011 V
b000 W
b0000000 X
b0000000 Y
0Z
b00000 \
b01010 ]
b00000000000000000000000000000000 _
b00000000000000000000000000000000 `
b00000000000000000000000000000100 a
b000000001100 b
1c
b00000000000000000000000000000100 f
#31
0c
#32
b00000000000000000000000000000100 1
b00000000000000000000000000010000 H
b00000000000000000000000000010100 I
b00000000000000000000000000000001 J
b00000000000101011000010110010011 P
b00000000000000000000000000010100 S
b00000000000000000000000000010001 T
b00001 \
b01011 ]
b00000000000000000000000000000001 `
b00000000000000000000000000000101 a
b000000010000 b
1c
b00000000000000000000000000000100 e
b00000000000000000000000000000101 f
#33
0c
